mongodb_atlas_api_sdk/__init__.py
mongodb_atlas_api_sdk/api_key.py
mongodb_atlas_api_sdk/atlas_api_sdk.py
mongodb_atlas_api_sdk/atlas_project.py
mongodb_atlas_api_sdk/database_user.py
mongodb_atlas_api_sdk/errors.py
mongodb_atlas_api_sdk-0.1.0.dist-info/LICENSE
mongodb_atlas_api_sdk-0.1.0.dist-info/WHEEL
mongodb_atlas_api_sdk-0.1.0.dist-info/METADATA
mongodb_atlas_api_sdk-0.1.0.dist-info/RECORD
