Metadata-Version: 2.1
Name: mongodb-atlas-api-sdk
Version: 0.1.0
Summary: MongoDB Atlas Admin API SDK
License: MPL-2.0
Author: johnpreston
Author-email: john@ews-network.net
Requires-Python: >=3.7,<4.0
Classifier: License :: OSI Approved
Classifier: Natural Language :: English
Classifier: Programming Language :: Python :: 3
Classifier: Programming Language :: Python :: 3.10
Classifier: Programming Language :: Python :: 3.7
Classifier: Programming Language :: Python :: 3.8
Classifier: Programming Language :: Python :: 3.9
Requires-Dist: awsipranges (>=0.3.1,<0.4.0)
Requires-Dist: compose-x-common (>=0.4.2,<0.5.0)
Requires-Dist: requests (>=2.27.1,<3.0.0)
